qcfinancial.cpython-311-x86_64-linux-gnu.so
qcfinancial-1.9.0.dist-info/METADATA
qcfinancial-1.9.0.dist-info/WHEEL
qcfinancial-1.9.0.dist-info/top_level.txt
qcfinancial-1.9.0.dist-info/RECORD
