Metadata-Version: 2.1
Name: qcfinancial
Version: 1.9.0
Summary: A Library for Valuation of Linear Interest Rate and FX Derivatives
Author: Alvaro Diaz V.
Author-email: alvaro@efaa.cl
Requires-Python: >=3.8
Provides-Extra: test
Requires-Dist: pytest>=6.0; extra == "test"
